{
  "openapi": "3.0.0",
  "info": {
    "title": "blog-api",
    "version": "1.0.0",
    "description": "A blog API with posts, comments, and authors"
  },
  "paths": {
    "/authorss": {
      "get": {
        "summary": "List authorss",
        "operationId": "listAuthorss",
        "parameters": [
          {
            "name": "limit",
            "in": "query",
            "schema": {
              "type": "integer"
            }
          },
          {
            "name": "offset",
            "in": "query",
            "schema": {
              "type": "integer"
            }
          }
        ],
        "responses": {
          "200": {
            "description": "Success",
            "content": {
              "application/json": {
                "schema": {
                  "type": "object",
                  "properties": {
                    "data": {
                      "type": "array",
                      "items": {
                        "$ref": "#/components/schemas/Authors"
                      }
                    },
                    "total": {
                      "type": "integer"
                    }
                  }
                }
              }
            }
          }
        }
      },
      "post": {
        "summary": "Create authors",
        "operationId": "createAuthors",
        "requestBody": {
          "required": true,
          "content": {
            "application/json": {
              "schema": {
                "$ref": "#/components/schemas/AuthorsCreate"
              }
            }
          }
        },
        "responses": {
          "201": {
            "description": "Created",
            "content": {
              "application/json": {
                "schema": {
                  "$ref": "#/components/schemas/Authors"
                }
              }
            }
          }
        }
      }
    },
    "/authorss/{id}": {
      "get": {
        "summary": "Get authors",
        "operationId": "getAuthors",
        "parameters": [
          {
            "name": "id",
            "in": "path",
            "required": true,
            "schema": {
              "type": "string"
            }
          }
        ],
        "responses": {
          "200": {
            "description": "Success",
            "content": {
              "application/json": {
                "schema": {
                  "$ref": "#/components/schemas/Authors"
                }
              }
            }
          }
        }
      },
      "put": {
        "summary": "Update authors",
        "operationId": "updateAuthors",
        "parameters": [
          {
            "name": "id",
            "in": "path",
            "required": true,
            "schema": {
              "type": "string"
            }
          }
        ],
        "requestBody": {
          "required": true,
          "content": {
            "application/json": {
              "schema": {
                "$ref": "#/components/schemas/AuthorsUpdate"
              }
            }
          }
        },
        "responses": {
          "200": {
            "description": "Success",
            "content": {
              "application/json": {
                "schema": {
                  "$ref": "#/components/schemas/Authors"
                }
              }
            }
          }
        }
      },
      "delete": {
        "summary": "Delete authors",
        "operationId": "deleteAuthors",
        "parameters": [
          {
            "name": "id",
            "in": "path",
            "required": true,
            "schema": {
              "type": "string"
            }
          }
        ],
        "responses": {
          "204": {
            "description": "Deleted"
          }
        }
      }
    },
    "/postss": {
      "get": {
        "summary": "List postss",
        "operationId": "listPostss",
        "parameters": [
          {
            "name": "limit",
            "in": "query",
            "schema": {
              "type": "integer"
            }
          },
          {
            "name": "offset",
            "in": "query",
            "schema": {
              "type": "integer"
            }
          }
        ],
        "responses": {
          "200": {
            "description": "Success",
            "content": {
              "application/json": {
                "schema": {
                  "type": "object",
                  "properties": {
                    "data": {
                      "type": "array",
                      "items": {
                        "$ref": "#/components/schemas/Posts"
                      }
                    },
                    "total": {
                      "type": "integer"
                    }
                  }
                }
              }
            }
          }
        }
      },
      "post": {
        "summary": "Create posts",
        "operationId": "createPosts",
        "requestBody": {
          "required": true,
          "content": {
            "application/json": {
              "schema": {
                "$ref": "#/components/schemas/PostsCreate"
              }
            }
          }
        },
        "responses": {
          "201": {
            "description": "Created",
            "content": {
              "application/json": {
                "schema": {
                  "$ref": "#/components/schemas/Posts"
                }
              }
            }
          }
        }
      }
    },
    "/postss/{id}": {
      "get": {
        "summary": "Get posts",
        "operationId": "getPosts",
        "parameters": [
          {
            "name": "id",
            "in": "path",
            "required": true,
            "schema": {
              "type": "string"
            }
          }
        ],
        "responses": {
          "200": {
            "description": "Success",
            "content": {
              "application/json": {
                "schema": {
                  "$ref": "#/components/schemas/Posts"
                }
              }
            }
          }
        }
      },
      "put": {
        "summary": "Update posts",
        "operationId": "updatePosts",
        "parameters": [
          {
            "name": "id",
            "in": "path",
            "required": true,
            "schema": {
              "type": "string"
            }
          }
        ],
        "requestBody": {
          "required": true,
          "content": {
            "application/json": {
              "schema": {
                "$ref": "#/components/schemas/PostsUpdate"
              }
            }
          }
        },
        "responses": {
          "200": {
            "description": "Success",
            "content": {
              "application/json": {
                "schema": {
                  "$ref": "#/components/schemas/Posts"
                }
              }
            }
          }
        }
      },
      "delete": {
        "summary": "Delete posts",
        "operationId": "deletePosts",
        "parameters": [
          {
            "name": "id",
            "in": "path",
            "required": true,
            "schema": {
              "type": "string"
            }
          }
        ],
        "responses": {
          "204": {
            "description": "Deleted"
          }
        }
      }
    },
    "/commentss": {
      "get": {
        "summary": "List commentss",
        "operationId": "listCommentss",
        "parameters": [
          {
            "name": "limit",
            "in": "query",
            "schema": {
              "type": "integer"
            }
          },
          {
            "name": "offset",
            "in": "query",
            "schema": {
              "type": "integer"
            }
          }
        ],
        "responses": {
          "200": {
            "description": "Success",
            "content": {
              "application/json": {
                "schema": {
                  "type": "object",
                  "properties": {
                    "data": {
                      "type": "array",
                      "items": {
                        "$ref": "#/components/schemas/Comments"
                      }
                    },
                    "total": {
                      "type": "integer"
                    }
                  }
                }
              }
            }
          }
        }
      },
      "post": {
        "summary": "Create comments",
        "operationId": "createComments",
        "requestBody": {
          "required": true,
          "content": {
            "application/json": {
              "schema": {
                "$ref": "#/components/schemas/CommentsCreate"
              }
            }
          }
        },
        "responses": {
          "201": {
            "description": "Created",
            "content": {
              "application/json": {
                "schema": {
                  "$ref": "#/components/schemas/Comments"
                }
              }
            }
          }
        }
      }
    },
    "/commentss/{id}": {
      "get": {
        "summary": "Get comments",
        "operationId": "getComments",
        "parameters": [
          {
            "name": "id",
            "in": "path",
            "required": true,
            "schema": {
              "type": "string"
            }
          }
        ],
        "responses": {
          "200": {
            "description": "Success",
            "content": {
              "application/json": {
                "schema": {
                  "$ref": "#/components/schemas/Comments"
                }
              }
            }
          }
        }
      },
      "put": {
        "summary": "Update comments",
        "operationId": "updateComments",
        "parameters": [
          {
            "name": "id",
            "in": "path",
            "required": true,
            "schema": {
              "type": "string"
            }
          }
        ],
        "requestBody": {
          "required": true,
          "content": {
            "application/json": {
              "schema": {
                "$ref": "#/components/schemas/CommentsUpdate"
              }
            }
          }
        },
        "responses": {
          "200": {
            "description": "Success",
            "content": {
              "application/json": {
                "schema": {
                  "$ref": "#/components/schemas/Comments"
                }
              }
            }
          }
        }
      },
      "delete": {
        "summary": "Delete comments",
        "operationId": "deleteComments",
        "parameters": [
          {
            "name": "id",
            "in": "path",
            "required": true,
            "schema": {
              "type": "string"
            }
          }
        ],
        "responses": {
          "204": {
            "description": "Deleted"
          }
        }
      }
    }
  },
  "components": {
    "schemas": {
      "Authors": {
        "type": "object",
        "properties": {
          "id": {
            "type": "string"
          },
          "email": {
            "type": "string",
            "format": "email"
          },
          "name": {
            "type": "string",
            "minLength": 2
          },
          "bio": {
            "type": "string"
          },
          "avatar": {
            "type": "string",
            "format": "uri"
          },
          "active": {
            "type": "boolean"
          },
          "createdAt": {
            "type": "string",
            "format": "date-time"
          },
          "updatedAt": {
            "type": "string",
            "format": "date-time"
          }
        }
      },
      "AuthorsCreate": {
        "type": "object",
        "required": [
          "email",
          "name"
        ],
        "properties": {
          "email": {
            "type": "string",
            "format": "email"
          },
          "name": {
            "type": "string",
            "minLength": 2
          },
          "bio": {
            "type": "string"
          },
          "avatar": {
            "type": "string",
            "format": "uri"
          },
          "active": {
            "type": "boolean"
          }
        }
      },
      "AuthorsUpdate": {
        "type": "object",
        "properties": {
          "email": {
            "type": "string",
            "format": "email"
          },
          "name": {
            "type": "string",
            "minLength": 2
          },
          "bio": {
            "type": "string"
          },
          "avatar": {
            "type": "string",
            "format": "uri"
          },
          "active": {
            "type": "boolean"
          }
        }
      },
      "Posts": {
        "type": "object",
        "properties": {
          "id": {
            "type": "string"
          },
          "title": {
            "type": "string",
            "minLength": 3,
            "maxLength": 200
          },
          "slug": {
            "type": "string"
          },
          "content": {
            "type": "string"
          },
          "excerpt": {
            "type": "string",
            "maxLength": 500
          },
          "authorId": {
            "type": "string",
            "format": "uuid"
          },
          "published": {
            "type": "boolean"
          },
          "publishedAt": {
            "type": "string",
            "format": "date-time"
          },
          "tags": {
            "type": "object"
          },
          "views": {
            "type": "integer"
          },
          "createdAt": {
            "type": "string",
            "format": "date-time"
          },
          "updatedAt": {
            "type": "string",
            "format": "date-time"
          }
        }
      },
      "PostsCreate": {
        "type": "object",
        "required": [
          "title",
          "slug",
          "content",
          "authorId"
        ],
        "properties": {
          "title": {
            "type": "string",
            "minLength": 3,
            "maxLength": 200
          },
          "slug": {
            "type": "string"
          },
          "content": {
            "type": "string"
          },
          "excerpt": {
            "type": "string",
            "maxLength": 500
          },
          "authorId": {
            "type": "string",
            "format": "uuid"
          },
          "published": {
            "type": "boolean"
          },
          "publishedAt": {
            "type": "string",
            "format": "date-time"
          },
          "tags": {
            "type": "object"
          },
          "views": {
            "type": "integer"
          }
        }
      },
      "PostsUpdate": {
        "type": "object",
        "properties": {
          "title": {
            "type": "string",
            "minLength": 3,
            "maxLength": 200
          },
          "slug": {
            "type": "string"
          },
          "content": {
            "type": "string"
          },
          "excerpt": {
            "type": "string",
            "maxLength": 500
          },
          "authorId": {
            "type": "string",
            "format": "uuid"
          },
          "published": {
            "type": "boolean"
          },
          "publishedAt": {
            "type": "string",
            "format": "date-time"
          },
          "tags": {
            "type": "object"
          },
          "views": {
            "type": "integer"
          }
        }
      },
      "Comments": {
        "type": "object",
        "properties": {
          "id": {
            "type": "string"
          },
          "postId": {
            "type": "string",
            "format": "uuid"
          },
          "authorEmail": {
            "type": "string",
            "format": "email"
          },
          "authorName": {
            "type": "string",
            "minLength": 2
          },
          "content": {
            "type": "string",
            "minLength": 1,
            "maxLength": 1000
          },
          "approved": {
            "type": "boolean"
          },
          "createdAt": {
            "type": "string",
            "format": "date-time"
          },
          "updatedAt": {
            "type": "string",
            "format": "date-time"
          }
        }
      },
      "CommentsCreate": {
        "type": "object",
        "required": [
          "postId",
          "authorEmail",
          "authorName",
          "content"
        ],
        "properties": {
          "postId": {
            "type": "string",
            "format": "uuid"
          },
          "authorEmail": {
            "type": "string",
            "format": "email"
          },
          "authorName": {
            "type": "string",
            "minLength": 2
          },
          "content": {
            "type": "string",
            "minLength": 1,
            "maxLength": 1000
          },
          "approved": {
            "type": "boolean"
          }
        }
      },
      "CommentsUpdate": {
        "type": "object",
        "properties": {
          "postId": {
            "type": "string",
            "format": "uuid"
          },
          "authorEmail": {
            "type": "string",
            "format": "email"
          },
          "authorName": {
            "type": "string",
            "minLength": 2
          },
          "content": {
            "type": "string",
            "minLength": 1,
            "maxLength": 1000
          },
          "approved": {
            "type": "boolean"
          }
        }
      }
    }
  }
}